dokuments/__init__.py
dokuments/arkitekt.py
dokuments/dokuments.py
dokuments/errors.py
dokuments/funcs.py
dokuments/py.typed
dokuments/rath.py
dokuments/rekuest.py
dokuments/api/project.json
dokuments/api/schema.graphql
dokuments/api/schema.py
dokuments-0.4.0.dist-info/METADATA
dokuments-0.4.0.dist-info/WHEEL
dokuments-0.4.0.dist-info/RECORD
